README.rst
setup.py
hardshare/__init__.py
hardshare/_version.py
hardshare/addons.py
hardshare/api.py
hardshare/cli.py
hardshare/core.py
hardshare/err.py
hardshare/mgmt.py
hardshare.egg-info/PKG-INFO
hardshare.egg-info/SOURCES.txt
hardshare.egg-info/dependency_links.txt
hardshare.egg-info/entry_points.txt
hardshare.egg-info/requires.txt
hardshare.egg-info/top_level.txt