Metadata-Version: 1.1
Name: hardshare
Version: 0.9.2
Summary: client (CLI and daemon) for the hardshare protocol
Home-page: https://github.com/rerobots/hardshare
Author: Scott C. Livingston
Author-email: q@rerobots.net
License: Apache 2.0
Platform: UNKNOWN
Classifier: License :: OSI Approved :: Apache Software License
Classifier: Programming Language :: Python :: 3
Classifier: Programming Language :: Python :: 3.5
Classifier: Programming Language :: Python :: 3.6
Classifier: Programming Language :: Python :: 3.7
Classifier: Programming Language :: Python :: 3.8
